{
    "display": {
        "icon": {
            "item": "minecraft:warped_nylium"
        },
        "title": {"translate":"The Nether Regions"},
        "description": {"translate":"Explore every Nether biome"},
        "frame": "goal"
    },
    "parent": "blazeandcave:nether/twisted",	
    "rewards": {
        "experience": 100,
		"function": "bc_rewards:nether/the_nether_regions"
    },	
    "criteria": {
        "nether_wastes": {
            "trigger": "minecraft:location",
            "conditions": {
                "biome": "minecraft:nether_wastes"
            }
        },
        "crimson_forest": {
            "trigger": "minecraft:location",
            "conditions": {
                "biome": "minecraft:crimson_forest"
            }
        },
        "warped_forest": {
            "trigger": "minecraft:location",
            "conditions": {
                "biome": "minecraft:warped_forest"
            }
        },
        "soul_sand_valley": {
            "trigger": "minecraft:location",
            "conditions": {
                "biome": "minecraft:soul_sand_valley"
            }
        }
    }
}